femlium/__init__.py
femlium/base_mesh_plotter.py
femlium/base_plotter.py
femlium/base_solution_plotter.py
femlium/dolfinx_plotter.py
femlium/domain_plotter.py
femlium/firedrake_plotter.py
femlium/meshio_plotter.py
femlium/numpy_plotter.py
femlium/utils/__init__.py
femlium/utils/colorbar_wrapper.py
femlium/utils/geojson_with_arrows.py
femlium/utils/transformer_wrapper.py
femlium-0.1.1.dist-info/licenses/AUTHORS
femlium-0.1.1.dist-info/licenses/LICENSE
femlium-0.1.1.dist-info/METADATA
femlium-0.1.1.dist-info/WHEEL
femlium-0.1.1.dist-info/top_level.txt
femlium-0.1.1.dist-info/RECORD
